boldi/_backup_version.py
boldi/backup.py
boldi_backup-0.9.7.dist-info/METADATA
boldi_backup-0.9.7.dist-info/WHEEL
boldi_backup-0.9.7.dist-info/entry_points.txt
boldi_backup-0.9.7.dist-info/RECORD
