Metadata-Version: 2.4
Name: boldi-backup
Version: 0.9.7
Summary: boldi.backup part of Boldi's Python libraries
Author-email: Boldizsár Palotás <boldizsar.palotas@gmail.com>
License: MIT
Requires-Python: >=3.12
Requires-Dist: boldi-ctx==0.9.7
Requires-Dist: tomli
